clivenv/__init__.py
clivenv/venv.py
clivenv-0.0.5.data/scripts/venv
clivenv-0.0.5.data/scripts/venv_pip_recording
clivenv-0.0.5.dist-info/METADATA
clivenv-0.0.5.dist-info/RECORD
clivenv-0.0.5.dist-info/WHEEL
clivenv-0.0.5.dist-info/entry_points.txt
clivenv-0.0.5.dist-info/top_level.txt
