Metadata-Version: 2.1
Name: clivenv
Version: 0.0.5
Summary: Fast access/manage to virtualenv between different python versions.
Home-page: https://github.com/duckingod/clivenv
Author: duckingod
Author-email: kingoduck@gmail.com
License: UNKNOWN
Platform: UNKNOWN
Classifier: Programming Language :: Python :: 3
Classifier: License :: OSI Approved :: MIT License
Classifier: Environment :: Console
Requires-Dist: virtualenv
